Metadata-Version: 2.1
Name: loragateway
Version: 0.4
Summary: lora gateway
Home-page: https://github.com/nbdy/loragateway
Author: Pascal Eberlein
Author-email: pascal@eberlein.io
License: UNKNOWN
Keywords: lora gateway
Platform: UNKNOWN
Classifier: Intended Audience :: Developers
Classifier: Topic :: Software Development :: Build Tools
Classifier: License :: OSI Approved :: MIT License
License-File: LICENSE.txt
